LICENSE.txt
MANIFEST.in
README.rst
requirements.txt
setup.py
bin/msgiver
msgiver/__init__.py
msgiver/__main__.py
msgiver/configure.py
msgiver/gist.py
msgiver/msg_base.py
msgiver/setting_base.py
msgiver/slack.py
msgiver.egg-info/PKG-INFO
msgiver.egg-info/SOURCES.txt
msgiver.egg-info/dependency_links.txt
msgiver.egg-info/requires.txt
msgiver.egg-info/top_level.txt