Metadata-Version: 1.1
Name: msgiver
Version: 0.1.6
Summary: msgiver will deliver the text to Messenger
Home-page: https://github.com/kitaro-tn/msgiver
Author: Tatsunori Nishikori
Author-email: tora.1986.tatsu@gmail.com
License: MIT
Platform: UNKNOWN
Classifier: Programming Language :: Python :: 2
Classifier: Programming Language :: Python :: 2.7
Classifier: Programming Language :: Python :: 3
Classifier: Programming Language :: Python :: 3.3
Classifier: Programming Language :: Python :: 3.4
Classifier: License :: OSI Approved :: MIT License
